{
  "version": "5.5.0",
  "flags": {},
  "shapes": [
    {
      "label": "crease",
      "points": [
        [
          1398.8260869565217,
          4059.565217391304
        ],
        [
          1590.1304347826087,
          4059.565217391304
        ],
        [
          2207.521739130435,
          2233.478260869565
        ],
        [
          2742.304347826087,
          1029.130434782609
        ],
        [
          2659.695652173913,
          985.6521739130437
        ],
        [
          1890.1304347826085,
          2281.304347826087
        ],
        [
          1768.391304347826,
          2872.608695652174
        ]
      ],
      "group_id": null,
      "description": "",
      "shape_type": "polygon",
      "flags": {},
      "mask": null
    },
    {
      "label": "crease",
      "points": [
        [
          2890.1304347826085,
          2016.0869565217392
        ],
        [
          2842.304347826087,
          2242.173913043478
        ],
        [
          11.869565217391397,
          2024.7826086956522
        ],
        [
          11.869565217391397,
          1794.3478260869567
        ],
        [
          1311.8695652173913,
          1920.4347826086957
        ],
        [
          1851.0,
          1876.9565217391305
        ]
      ],
      "group_id": null,
      "description": "",
      "shape_type": "polygon",
      "flags": {},
      "mask": null
    }
  ],
  "imagePath": "Card (58).jpg",
  "imageData": null,
  "imageHeight": 4080,
  "imageWidth": 2902
}